route/__init__.py
tests/__init__.py
string_routing-0.0.1.dist-info/LICENSE
string_routing-0.0.1.dist-info/METADATA
string_routing-0.0.1.dist-info/WHEEL
string_routing-0.0.1.dist-info/top_level.txt
string_routing-0.0.1.dist-info/RECORD
