Metadata-Version: 2.1
Name: string-routing
Version: 0.0.1
Summary: A simple way to link strings to functions
Home-page: https://github.com/gregoryerik/string-routing
Author: Gregory Erik
Author-email: 
License: UNKNOWN
Platform: UNKNOWN
Classifier: Programming Language :: Python :: 3
Classifier: License :: OSI Approved :: MIT License
Classifier: Operating System :: OS Independent
Requires-Python: >=3.6
